[{"first_name":"Esteban","last_name":"Thaw","associate_id":"ethaw0","email":"ethaw0@newyorker.com","role_profile":"Associate","user_id":763028,"password":"nlDi2XAON7J7","aup_certified":true},
{"first_name":"Rania","last_name":"Moxson","associate_id":"rmoxson1","email":"rmoxson1@amazon.com","role_profile":"Talent Enablement Lead","user_id":363252,"password":"9PQOVLvwV3n","aup_certified":false},
{"first_name":"Crosby","last_name":"Wong","associate_id":"cwong2","email":"cwong2@apple.com","role_profile":"Competency Lead","user_id":570042,"password":"DJLoyp7TIjcR","aup_certified":false},
{"first_name":"Keenan","last_name":"Wethered","associate_id":"kwethered3","email":"kwethered3@pbs.org","role_profile":"Competency Lead","user_id":139010,"password":"HQFoadjHl","aup_certified":true},
{"first_name":"Jany","last_name":"Cradock","associate_id":"jcradock4","email":"jcradock4@skyrock.com","role_profile":"Associate","user_id":390153,"password":"ldgI3Z4FRMtV","aup_certified":false},
{"first_name":"Shelli","last_name":"Grigoriscu","associate_id":"sgrigoriscu5","email":"sgrigoriscu5@goo.ne.jp","role_profile":"Talent Enablement Lead","user_id":659683,"password":"uHmHU3yS3U","aup_certified":true},
{"first_name":"Cheri","last_name":"Kernocke","associate_id":"ckernocke6","email":"ckernocke6@woothemes.com","role_profile":"Associate","user_id":391343,"password":"XlHjrpt","aup_certified":true},
{"first_name":"Lavena","last_name":"Aitken","associate_id":"laitken7","email":"laitken7@naver.com","role_profile":"Competency Lead","user_id":313721,"password":"GVWgRYab","aup_certified":true},
{"first_name":"Gail","last_name":"Woloschinski","associate_id":"gwoloschinski8","email":"gwoloschinski8@census.gov","role_profile":"Talent Enablement Lead","user_id":738047,"password":"ykzlogiVDS","aup_certified":true},
{"first_name":"Freddi","last_name":"Mattholie","associate_id":"fmattholie9","email":"fmattholie9@networkadvertising.org","role_profile":"Supervisor","user_id":288769,"password":"n9NnkTu","aup_certified":true},
{"first_name":"Gerhard","last_name":"Morpeth","associate_id":"gmorpetha","email":"gmorpetha@usa.gov","role_profile":"Talent Enablement Lead","user_id":894538,"password":"sxBxYoKKTA","aup_certified":false},
{"first_name":"Klarika","last_name":"Shemmin","associate_id":"kshemminb","email":"kshemminb@senate.gov","role_profile":"Associate","user_id":168031,"password":"FboSF4Kza2H","aup_certified":true},
{"first_name":"Annice","last_name":"Humpherston","associate_id":"ahumpherstonc","email":"ahumpherstonc@senate.gov","role_profile":"Talent Enablement Lead","user_id":778353,"password":"dUBopCVuqOTT","aup_certified":false},
{"first_name":"Stephine","last_name":"Marlor","associate_id":"smarlord","email":"smarlord@cdbaby.com","role_profile":"Supervisor","user_id":210166,"password":"4tBAE7jmF2","aup_certified":false},
{"first_name":"Donica","last_name":"Eastment","associate_id":"deastmente","email":"deastmente@slashdot.org","role_profile":"Competency Lead","user_id":477509,"password":"WCYFZnN8K","aup_certified":true},
{"first_name":"Tanny","last_name":"Croot","associate_id":"tcrootf","email":"tcrootf@surveymonkey.com","role_profile":"Supervisor","user_id":632511,"password":"cqkQOUbv7o","aup_certified":false},
{"first_name":"Quentin","last_name":"Venditto","associate_id":"qvendittog","email":"qvendittog@blinklist.com","role_profile":"Talent Enablement Lead","user_id":520405,"password":"BsqRL0nrKBYO","aup_certified":false},
{"first_name":"Jammie","last_name":"Loveredge","associate_id":"jloveredgeh","email":"jloveredgeh@devhub.com","role_profile":"Competency Lead","user_id":432339,"password":"wAsjq5bfqe","aup_certified":true},
{"first_name":"Jeannie","last_name":"Drage","associate_id":"jdragei","email":"jdragei@alibaba.com","role_profile":"Talent Enablement Lead","user_id":472858,"password":"AOO5ARZE","aup_certified":false},
{"first_name":"Nola","last_name":"Talloe","associate_id":"ntalloej","email":"ntalloej@networkadvertising.org","role_profile":"Competency Lead","user_id":167905,"password":"RwRfi8o","aup_certified":false},
{"first_name":"Ozzie","last_name":"Bennet","associate_id":"obennetk","email":"obennetk@addthis.com","role_profile":"Talent Enablement Lead","user_id":119509,"password":"B5UwuA","aup_certified":false},
{"first_name":"Wynny","last_name":"Gilfoy","associate_id":"wgilfoyl","email":"wgilfoyl@mediafire.com","role_profile":"Supervisor","user_id":62852,"password":"7CVHJ4Ffwf0","aup_certified":true},
{"first_name":"Raul","last_name":"Roggero","associate_id":"rroggerom","email":"rroggerom@plala.or.jp","role_profile":"Associate","user_id":102761,"password":"mWFyQ2b","aup_certified":false},
{"first_name":"Laureen","last_name":"Sterry","associate_id":"lsterryn","email":"lsterryn@un.org","role_profile":"Supervisor","user_id":745022,"password":"S54GE3LjA0B","aup_certified":false},
{"first_name":"Leland","last_name":"McKenny","associate_id":"lmckennyo","email":"lmckennyo@infoseek.co.jp","role_profile":"Supervisor","user_id":810828,"password":"f525tTFC","aup_certified":false},
{"first_name":"Leona","last_name":"Colnett","associate_id":"lcolnettp","email":"lcolnettp@buzzfeed.com","role_profile":"Competency Lead","user_id":303682,"password":"LZ8IAmhHhE","aup_certified":true},
{"first_name":"Isa","last_name":"Leyburn","associate_id":"ileyburnq","email":"ileyburnq@unc.edu","role_profile":"Supervisor","user_id":498325,"password":"dWAj6nF40","aup_certified":false},
{"first_name":"Margret","last_name":"Brixey","associate_id":"mbrixeyr","email":"mbrixeyr@skype.com","role_profile":"Competency Lead","user_id":214256,"password":"cZcbVINCv","aup_certified":true},
{"first_name":"Laraine","last_name":"Philipet","associate_id":"lphilipets","email":"lphilipets@dion.ne.jp","role_profile":"Competency Lead","user_id":878128,"password":"J6OrhmTTy","aup_certified":false},
{"first_name":"Joela","last_name":"Dyka","associate_id":"jdykat","email":"jdykat@blogs.com","role_profile":"Associate","user_id":871000,"password":"BmfPsNewRdv","aup_certified":true},
{"first_name":"Egan","last_name":"Ertelt","associate_id":"eerteltu","email":"eerteltu@skype.com","role_profile":"Competency Lead","user_id":653336,"password":"YGTwSPx4QswK","aup_certified":false},
{"first_name":"Norbert","last_name":"Dursley","associate_id":"ndursleyv","email":"ndursleyv@house.gov","role_profile":"Competency Lead","user_id":127880,"password":"1FvO1Gc","aup_certified":true},
{"first_name":"Augustine","last_name":"Beeble","associate_id":"abeeblew","email":"abeeblew@house.gov","role_profile":"Supervisor","user_id":530940,"password":"RLZP5kzCHms","aup_certified":true},
{"first_name":"Hulda","last_name":"Faircloth","associate_id":"hfairclothx","email":"hfairclothx@indiatimes.com","role_profile":"Talent Enablement Lead","user_id":633831,"password":"MdVL1tQ2itJ1","aup_certified":false},
{"first_name":"Tressa","last_name":"Arnefield","associate_id":"tarnefieldy","email":"tarnefieldy@psu.edu","role_profile":"Supervisor","user_id":329288,"password":"lV42GMXu","aup_certified":true},
{"first_name":"Rosalynd","last_name":"Steart","associate_id":"rsteartz","email":"rsteartz@t.co","role_profile":"Supervisor","user_id":670990,"password":"hE53UUZLNEJs","aup_certified":true},
{"first_name":"Teddie","last_name":"Van de Velde","associate_id":"tvandevelde10","email":"tvandevelde10@cam.ac.uk","role_profile":"Talent Enablement Lead","user_id":631446,"password":"QyQlB6q3172P","aup_certified":false},
{"first_name":"Shalom","last_name":"Nicolson","associate_id":"snicolson11","email":"snicolson11@gnu.org","role_profile":"Associate","user_id":21151,"password":"CYbr44zuQ","aup_certified":true},
{"first_name":"Yance","last_name":"Berrigan","associate_id":"yberrigan12","email":"yberrigan12@marketwatch.com","role_profile":"Associate","user_id":730453,"password":"8ns5ua1J","aup_certified":true},
{"first_name":"Shayne","last_name":"McCool","associate_id":"smccool13","email":"smccool13@utexas.edu","role_profile":"Talent Enablement Lead","user_id":284684,"password":"DxFVY5","aup_certified":true},
{"first_name":"Alecia","last_name":"Westby","associate_id":"awestby14","email":"awestby14@altervista.org","role_profile":"Associate","user_id":91427,"password":"7mt7T7Bw","aup_certified":false},
{"first_name":"Glori","last_name":"Rowland","associate_id":"growland15","email":"growland15@berkeley.edu","role_profile":"Competency Lead","user_id":335386,"password":"ozNUiyn","aup_certified":true},
{"first_name":"Rochell","last_name":"Clappison","associate_id":"rclappison16","email":"rclappison16@blogspot.com","role_profile":"Supervisor","user_id":307723,"password":"95KpU1z0VT","aup_certified":true},
{"first_name":"Arther","last_name":"Thatcham","associate_id":"athatcham17","email":"athatcham17@simplemachines.org","role_profile":"Supervisor","user_id":807504,"password":"NjvzLWn","aup_certified":true},
{"first_name":"Dorelia","last_name":"Tinto","associate_id":"dtinto18","email":"dtinto18@google.com.au","role_profile":"Competency Lead","user_id":884807,"password":"acC5pdqxc","aup_certified":false},
{"first_name":"Dennet","last_name":"Tupling","associate_id":"dtupling19","email":"dtupling19@apache.org","role_profile":"Talent Enablement Lead","user_id":282760,"password":"HSLSUjQvU1","aup_certified":true},
{"first_name":"Susanetta","last_name":"Renac","associate_id":"srenac1a","email":"srenac1a@geocities.com","role_profile":"Associate","user_id":489774,"password":"7TqDtr","aup_certified":true},
{"first_name":"Verena","last_name":"Stainfield","associate_id":"vstainfield1b","email":"vstainfield1b@ycombinator.com","role_profile":"Competency Lead","user_id":260606,"password":"pYMONoouv","aup_certified":true},
{"first_name":"Pierrette","last_name":"Jansky","associate_id":"pjansky1c","email":"pjansky1c@dedecms.com","role_profile":"Competency Lead","user_id":824100,"password":"huu7X0W","aup_certified":false},
{"first_name":"Xenia","last_name":"Von Der Empten","associate_id":"xvonderempten1d","email":"xvonderempten1d@theatlantic.com","role_profile":"Supervisor","user_id":461441,"password":"v9CTiy","aup_certified":true},
{"first_name":"Cathryn","last_name":"St Clair","associate_id":"cstclair1e","email":"cstclair1e@google.ru","role_profile":"Supervisor","user_id":592105,"password":"IxrOlJa","aup_certified":false},
{"first_name":"Esma","last_name":"Scryne","associate_id":"escryne1f","email":"escryne1f@gov.uk","role_profile":"Supervisor","user_id":844088,"password":"9K9Zl1MPmcT","aup_certified":false},
{"first_name":"Deeann","last_name":"MacRory","associate_id":"dmacrory1g","email":"dmacrory1g@tripadvisor.com","role_profile":"Talent Enablement Lead","user_id":573734,"password":"emPeEroe8HU4","aup_certified":true},
{"first_name":"Clo","last_name":"Puckrin","associate_id":"cpuckrin1h","email":"cpuckrin1h@creativecommons.org","role_profile":"Associate","user_id":193335,"password":"6bFTjrZIYu6W","aup_certified":false},
{"first_name":"Katleen","last_name":"Vanderson","associate_id":"kvanderson1i","email":"kvanderson1i@whitehouse.gov","role_profile":"Associate","user_id":812936,"password":"5uTqeVLTJf","aup_certified":true},
{"first_name":"Alvy","last_name":"Sawyer","associate_id":"asawyer1j","email":"asawyer1j@google.co.uk","role_profile":"Associate","user_id":39537,"password":"5atddK","aup_certified":false},
{"first_name":"Erika","last_name":"Kingswood","associate_id":"ekingswood1k","email":"ekingswood1k@gizmodo.com","role_profile":"Competency Lead","user_id":682867,"password":"GMFKird","aup_certified":true},
{"first_name":"Marc","last_name":"Lynes","associate_id":"mlynes1l","email":"mlynes1l@digg.com","role_profile":"Supervisor","user_id":94285,"password":"1KuOTxTA5jV","aup_certified":false},
{"first_name":"Alex","last_name":"Heasley","associate_id":"aheasley1m","email":"aheasley1m@shareasale.com","role_profile":"Associate","user_id":338789,"password":"338fE7hPX0","aup_certified":false},
{"first_name":"Estelle","last_name":"Biasotti","associate_id":"ebiasotti1n","email":"ebiasotti1n@gravatar.com","role_profile":"Competency Lead","user_id":447567,"password":"1wC4sFYx91","aup_certified":false},
{"first_name":"Jessie","last_name":"Rockwill","associate_id":"jrockwill1o","email":"jrockwill1o@goodreads.com","role_profile":"Supervisor","user_id":929436,"password":"ZlNhUK","aup_certified":false},
{"first_name":"Nertie","last_name":"Cod","associate_id":"ncod1p","email":"ncod1p@skype.com","role_profile":"Associate","user_id":503220,"password":"21z0hGsW","aup_certified":false},
{"first_name":"Selia","last_name":"Fawson","associate_id":"sfawson1q","email":"sfawson1q@buzzfeed.com","role_profile":"Competency Lead","user_id":656495,"password":"74j6yiP7mtLi","aup_certified":true},
{"first_name":"Virginie","last_name":"Kempstone","associate_id":"vkempstone1r","email":"vkempstone1r@blinklist.com","role_profile":"Associate","user_id":675537,"password":"CWDRgtaF","aup_certified":true},
{"first_name":"Chere","last_name":"Blunsen","associate_id":"cblunsen1s","email":"cblunsen1s@simplemachines.org","role_profile":"Talent Enablement Lead","user_id":703462,"password":"nK0Q98vzkJHH","aup_certified":true},
{"first_name":"Othelia","last_name":"Crome","associate_id":"ocrome1t","email":"ocrome1t@usa.gov","role_profile":"Associate","user_id":104177,"password":"NMqAlqv","aup_certified":false},
{"first_name":"Dev","last_name":"Doctor","associate_id":"ddoctor1u","email":"ddoctor1u@theglobeandmail.com","role_profile":"Supervisor","user_id":344197,"password":"h3YHxbFp","aup_certified":false},
{"first_name":"Cybil","last_name":"Yukhov","associate_id":"cyukhov1v","email":"cyukhov1v@zdnet.com","role_profile":"Talent Enablement Lead","user_id":141796,"password":"xaWSjVZxnyZ","aup_certified":false},
{"first_name":"Hilde","last_name":"Conelly","associate_id":"hconelly1w","email":"hconelly1w@reverbnation.com","role_profile":"Talent Enablement Lead","user_id":519250,"password":"edJ7sv0","aup_certified":false},
{"first_name":"Melantha","last_name":"Kraft","associate_id":"mkraft1x","email":"mkraft1x@smugmug.com","role_profile":"Supervisor","user_id":283339,"password":"UDpjFO8p","aup_certified":false},
{"first_name":"Mollie","last_name":"Crampsy","associate_id":"mcrampsy1y","email":"mcrampsy1y@plala.or.jp","role_profile":"Supervisor","user_id":671825,"password":"6F6m47v","aup_certified":true},
{"first_name":"Darrelle","last_name":"Dalman","associate_id":"ddalman1z","email":"ddalman1z@narod.ru","role_profile":"Associate","user_id":962604,"password":"46kkSddJH","aup_certified":true},
{"first_name":"Huntley","last_name":"Gudd","associate_id":"hgudd20","email":"hgudd20@smugmug.com","role_profile":"Supervisor","user_id":100692,"password":"0qXW94xkQCRP","aup_certified":false},
{"first_name":"Kiri","last_name":"Larkings","associate_id":"klarkings21","email":"klarkings21@virginia.edu","role_profile":"Associate","user_id":322307,"password":"bsuUYo","aup_certified":true},
{"first_name":"Shana","last_name":"Beernt","associate_id":"sbeernt22","email":"sbeernt22@deliciousdays.com","role_profile":"Talent Enablement Lead","user_id":30400,"password":"DQUbtiTQ","aup_certified":true},
{"first_name":"Cecile","last_name":"Rumens","associate_id":"crumens23","email":"crumens23@xing.com","role_profile":"Talent Enablement Lead","user_id":146057,"password":"8k3kO5","aup_certified":true},
{"first_name":"Kandace","last_name":"Defty","associate_id":"kdefty24","email":"kdefty24@mayoclinic.com","role_profile":"Competency Lead","user_id":863822,"password":"A3PIUAmz","aup_certified":true},
{"first_name":"Ewart","last_name":"Bletsoe","associate_id":"ebletsoe25","email":"ebletsoe25@oracle.com","role_profile":"Supervisor","user_id":1091,"password":"IAtG6ywjvwB","aup_certified":false},
{"first_name":"Malena","last_name":"Girardoni","associate_id":"mgirardoni26","email":"mgirardoni26@webs.com","role_profile":"Supervisor","user_id":736804,"password":"vBdUSx7ZBMBs","aup_certified":false},
{"first_name":"Dougy","last_name":"Cumbridge","associate_id":"dcumbridge27","email":"dcumbridge27@vinaora.com","role_profile":"Supervisor","user_id":214226,"password":"snizo6Mu9is5","aup_certified":false},
{"first_name":"Jae","last_name":"Messingham","associate_id":"jmessingham28","email":"jmessingham28@marketwatch.com","role_profile":"Supervisor","user_id":388304,"password":"JEDYMvKL8iY","aup_certified":true},
{"first_name":"Tyler","last_name":"Grushin","associate_id":"tgrushin29","email":"tgrushin29@hhs.gov","role_profile":"Supervisor","user_id":818498,"password":"4pNtW0NEXg","aup_certified":true},
{"first_name":"Ceil","last_name":"Hunnawill","associate_id":"chunnawill2a","email":"chunnawill2a@php.net","role_profile":"Associate","user_id":788690,"password":"NS9TrnCSk","aup_certified":false},
{"first_name":"Una","last_name":"Kezar","associate_id":"ukezar2b","email":"ukezar2b@uiuc.edu","role_profile":"Talent Enablement Lead","user_id":80720,"password":"7Vegd6hrmM","aup_certified":true},
{"first_name":"Ilene","last_name":"O'Brollachain","associate_id":"iobrollachain2c","email":"iobrollachain2c@lulu.com","role_profile":"Supervisor","user_id":416768,"password":"oV4w3mo4QZY7","aup_certified":false},
{"first_name":"Ardra","last_name":"Chaffen","associate_id":"achaffen2d","email":"achaffen2d@hp.com","role_profile":"Competency Lead","user_id":391427,"password":"TCtokpExT","aup_certified":false},
{"first_name":"Penny","last_name":"Dybbe","associate_id":"pdybbe2e","email":"pdybbe2e@earthlink.net","role_profile":"Supervisor","user_id":718825,"password":"JVYCAk1DI","aup_certified":true},
{"first_name":"Angelika","last_name":"Bensusan","associate_id":"abensusan2f","email":"abensusan2f@miitbeian.gov.cn","role_profile":"Associate","user_id":440467,"password":"ksqs3DA","aup_certified":true},
{"first_name":"Amble","last_name":"Bees","associate_id":"abees2g","email":"abees2g@scientificamerican.com","role_profile":"Talent Enablement Lead","user_id":817807,"password":"w6NVsJtm0Cw","aup_certified":false},
{"first_name":"Shannan","last_name":"Preene","associate_id":"spreene2h","email":"spreene2h@telegraph.co.uk","role_profile":"Competency Lead","user_id":440408,"password":"qmoCVbYs","aup_certified":true},
{"first_name":"Barbey","last_name":"Tremelling","associate_id":"btremelling2i","email":"btremelling2i@ibm.com","role_profile":"Competency Lead","user_id":867727,"password":"CeI9BF4ygFtp","aup_certified":true},
{"first_name":"Erhard","last_name":"Klaiser","associate_id":"eklaiser2j","email":"eklaiser2j@independent.co.uk","role_profile":"Associate","user_id":936834,"password":"XnFh0B","aup_certified":true},
{"first_name":"Etan","last_name":"Russi","associate_id":"erussi2k","email":"erussi2k@blog.com","role_profile":"Talent Enablement Lead","user_id":907171,"password":"NWqG71ZSrR","aup_certified":true},
{"first_name":"Burch","last_name":"Weatherall","associate_id":"bweatherall2l","email":"bweatherall2l@utexas.edu","role_profile":"Competency Lead","user_id":671831,"password":"f9ccAOy","aup_certified":false},
{"first_name":"Loni","last_name":"Boadby","associate_id":"lboadby2m","email":"lboadby2m@thetimes.co.uk","role_profile":"Associate","user_id":496183,"password":"CxW8E2Y","aup_certified":false},
{"first_name":"Donnajean","last_name":"Whitnell","associate_id":"dwhitnell2n","email":"dwhitnell2n@redcross.org","role_profile":"Talent Enablement Lead","user_id":917998,"password":"vKDGTz","aup_certified":false},
{"first_name":"Marilee","last_name":"Hackelton","associate_id":"mhackelton2o","email":"mhackelton2o@godaddy.com","role_profile":"Associate","user_id":607804,"password":"mDBoSFWzo","aup_certified":false},
{"first_name":"Maryjane","last_name":"Camm","associate_id":"mcamm2p","email":"mcamm2p@cyberchimps.com","role_profile":"Associate","user_id":561059,"password":"0SMTFmOwSX","aup_certified":false},
{"first_name":"Virgie","last_name":"Gradly","associate_id":"vgradly2q","email":"vgradly2q@youku.com","role_profile":"Competency Lead","user_id":340801,"password":"QJrsVPNHYPC","aup_certified":true},
{"first_name":"Petronella","last_name":"Mellsop","associate_id":"pmellsop2r","email":"pmellsop2r@de.vu","role_profile":"Supervisor","user_id":794348,"password":"7YitsPxUg","aup_certified":true},
{"first_name":"Wendie","last_name":"Copes","associate_id":"wcopes2s","email":"wcopes2s@yolasite.com","role_profile":"Talent Enablement Lead","user_id":725064,"password":"sYeD2I","aup_certified":true},
{"first_name":"Earl","last_name":"Piff","associate_id":"epiff2t","email":"epiff2t@multiply.com","role_profile":"Competency Lead","user_id":140529,"password":"GQxOBM9GFUhp","aup_certified":true},
{"first_name":"Charita","last_name":"Cobleigh","associate_id":"ccobleigh2u","email":"ccobleigh2u@slate.com","role_profile":"Talent Enablement Lead","user_id":64310,"password":"I45eYot8nBf","aup_certified":false},
{"first_name":"Koralle","last_name":"Saxelby","associate_id":"ksaxelby2v","email":"ksaxelby2v@wikispaces.com","role_profile":"Associate","user_id":807019,"password":"B7k6Vik","aup_certified":true},
{"first_name":"Ronna","last_name":"Potzold","associate_id":"rpotzold2w","email":"rpotzold2w@cdc.gov","role_profile":"Talent Enablement Lead","user_id":873823,"password":"P4rKpoWqtJg","aup_certified":true},
{"first_name":"Hill","last_name":"Lafee","associate_id":"hlafee2x","email":"hlafee2x@home.pl","role_profile":"Talent Enablement Lead","user_id":680184,"password":"DgHHwO7af","aup_certified":true},
{"first_name":"Filmer","last_name":"Lagneaux","associate_id":"flagneaux2y","email":"flagneaux2y@unblog.fr","role_profile":"Talent Enablement Lead","user_id":900393,"password":"d6hSnAGunXxd","aup_certified":true},
{"first_name":"Kerstin","last_name":"Atherton","associate_id":"katherton2z","email":"katherton2z@tinyurl.com","role_profile":"Talent Enablement Lead","user_id":245274,"password":"dswYHZso","aup_certified":false},
{"first_name":"Guthrey","last_name":"Dumsday","associate_id":"gdumsday30","email":"gdumsday30@alexa.com","role_profile":"Talent Enablement Lead","user_id":491738,"password":"8tBtu9CdEWr","aup_certified":true},
{"first_name":"Welch","last_name":"Rockliffe","associate_id":"wrockliffe31","email":"wrockliffe31@nhs.uk","role_profile":"Associate","user_id":526218,"password":"dk8B2eMZN4J1","aup_certified":true},
{"first_name":"Tadio","last_name":"Keal","associate_id":"tkeal32","email":"tkeal32@jugem.jp","role_profile":"Supervisor","user_id":102036,"password":"xu23twSzeCX5","aup_certified":false},
{"first_name":"Terrijo","last_name":"Garth","associate_id":"tgarth33","email":"tgarth33@phoca.cz","role_profile":"Talent Enablement Lead","user_id":230929,"password":"W4psri8","aup_certified":true},
{"first_name":"Verney","last_name":"Greenhow","associate_id":"vgreenhow34","email":"vgreenhow34@google.nl","role_profile":"Associate","user_id":694629,"password":"bfSUAU79a","aup_certified":true},
{"first_name":"Cross","last_name":"Dradey","associate_id":"cdradey35","email":"cdradey35@google.co.jp","role_profile":"Supervisor","user_id":568548,"password":"xBH2YnT2ox1y","aup_certified":true},
{"first_name":"Augustus","last_name":"Shulem","associate_id":"ashulem36","email":"ashulem36@shop-pro.jp","role_profile":"Associate","user_id":298294,"password":"MBFMSjG1Xvc","aup_certified":true},
{"first_name":"Marylou","last_name":"Cherry Holme","associate_id":"mcherryholme37","email":"mcherryholme37@skype.com","role_profile":"Supervisor","user_id":587821,"password":"6pj0QXrvqZ","aup_certified":true},
{"first_name":"Sylvan","last_name":"Tregear","associate_id":"stregear38","email":"stregear38@yandex.ru","role_profile":"Competency Lead","user_id":498408,"password":"AGOAWLgpXq5","aup_certified":false},
{"first_name":"Gerty","last_name":"Gelly","associate_id":"ggelly39","email":"ggelly39@mayoclinic.com","role_profile":"Talent Enablement Lead","user_id":668193,"password":"ldd7ITZNqT","aup_certified":false},
{"first_name":"Bibby","last_name":"Cardew","associate_id":"bcardew3a","email":"bcardew3a@netvibes.com","role_profile":"Supervisor","user_id":104828,"password":"NU1Iz4XcmZb","aup_certified":false},
{"first_name":"Stavro","last_name":"Thomson","associate_id":"sthomson3b","email":"sthomson3b@shutterfly.com","role_profile":"Associate","user_id":498673,"password":"UOSmvCa","aup_certified":true},
{"first_name":"Merrill","last_name":"Cutchie","associate_id":"mcutchie3c","email":"mcutchie3c@slideshare.net","role_profile":"Supervisor","user_id":683278,"password":"Pm0j7VmwK","aup_certified":false},
{"first_name":"Frasier","last_name":"Checketts","associate_id":"fchecketts3d","email":"fchecketts3d@oracle.com","role_profile":"Supervisor","user_id":560621,"password":"UmJ6n1iIu4bX","aup_certified":true},
{"first_name":"Fraser","last_name":"Dudny","associate_id":"fdudny3e","email":"fdudny3e@fc2.com","role_profile":"Supervisor","user_id":804382,"password":"CuzKkBNVOGz","aup_certified":true},
{"first_name":"Erastus","last_name":"Seaborn","associate_id":"eseaborn3f","email":"eseaborn3f@blogger.com","role_profile":"Competency Lead","user_id":747626,"password":"m660Niy2","aup_certified":false},
{"first_name":"Susie","last_name":"Stivey","associate_id":"sstivey3g","email":"sstivey3g@symantec.com","role_profile":"Associate","user_id":685618,"password":"E0XdyRdWIb","aup_certified":true},
{"first_name":"Gordy","last_name":"Mitrikhin","associate_id":"gmitrikhin3h","email":"gmitrikhin3h@amazon.com","role_profile":"Talent Enablement Lead","user_id":496144,"password":"2AaxBInf","aup_certified":false},
{"first_name":"Juliann","last_name":"Sivier","associate_id":"jsivier3i","email":"jsivier3i@furl.net","role_profile":"Supervisor","user_id":929019,"password":"BUftY9D8wjg","aup_certified":false},
{"first_name":"Joy","last_name":"Lumbers","associate_id":"jlumbers3j","email":"jlumbers3j@rambler.ru","role_profile":"Competency Lead","user_id":215344,"password":"SFIxWXYcV","aup_certified":false},
{"first_name":"Dur","last_name":"Goodisson","associate_id":"dgoodisson3k","email":"dgoodisson3k@flavors.me","role_profile":"Supervisor","user_id":16162,"password":"mjpOiPL","aup_certified":true},
{"first_name":"Frederico","last_name":"Doyley","associate_id":"fdoyley3l","email":"fdoyley3l@amazon.de","role_profile":"Talent Enablement Lead","user_id":527898,"password":"NKhuzYsIv","aup_certified":false},
{"first_name":"Dallas","last_name":"Allsopp","associate_id":"dallsopp3m","email":"dallsopp3m@about.me","role_profile":"Talent Enablement Lead","user_id":991040,"password":"pR9PjsyBwDZ","aup_certified":true},
{"first_name":"Buckie","last_name":"Scoggin","associate_id":"bscoggin3n","email":"bscoggin3n@dyndns.org","role_profile":"Talent Enablement Lead","user_id":483827,"password":"V6dfHj","aup_certified":false},
{"first_name":"Ofilia","last_name":"Mattielli","associate_id":"omattielli3o","email":"omattielli3o@ameblo.jp","role_profile":"Competency Lead","user_id":754197,"password":"yT8bQWeKMMg","aup_certified":true},
{"first_name":"Gianna","last_name":"Cromly","associate_id":"gcromly3p","email":"gcromly3p@economist.com","role_profile":"Associate","user_id":340126,"password":"b3QJNB7E","aup_certified":true},
{"first_name":"Micheal","last_name":"Loudiane","associate_id":"mloudiane3q","email":"mloudiane3q@prlog.org","role_profile":"Associate","user_id":749419,"password":"xhPrRP","aup_certified":true},
{"first_name":"Fernanda","last_name":"Jesteco","associate_id":"fjesteco3r","email":"fjesteco3r@shutterfly.com","role_profile":"Supervisor","user_id":204230,"password":"bP8izqAFUkUD","aup_certified":true},
{"first_name":"Corri","last_name":"Hoggetts","associate_id":"choggetts3s","email":"choggetts3s@parallels.com","role_profile":"Competency Lead","user_id":459021,"password":"Hh12sQ","aup_certified":true},
{"first_name":"Quentin","last_name":"Djurisic","associate_id":"qdjurisic3t","email":"qdjurisic3t@pbs.org","role_profile":"Competency Lead","user_id":776851,"password":"UH2rpp","aup_certified":true},
{"first_name":"Rosaline","last_name":"Beattie","associate_id":"rbeattie3u","email":"rbeattie3u@wikia.com","role_profile":"Associate","user_id":503783,"password":"UfCzSngrbVGV","aup_certified":true},
{"first_name":"Hedwig","last_name":"Ciotti","associate_id":"hciotti3v","email":"hciotti3v@g.co","role_profile":"Supervisor","user_id":303880,"password":"4UwgatHW","aup_certified":false},
{"first_name":"Delcine","last_name":"Mugg","associate_id":"dmugg3w","email":"dmugg3w@hostgator.com","role_profile":"Associate","user_id":789923,"password":"qKarcJRSbey","aup_certified":false},
{"first_name":"Christyna","last_name":"Linscott","associate_id":"clinscott3x","email":"clinscott3x@woothemes.com","role_profile":"Talent Enablement Lead","user_id":268522,"password":"ywnSP3","aup_certified":true},
{"first_name":"Carolyn","last_name":"Josebury","associate_id":"cjosebury3y","email":"cjosebury3y@hexun.com","role_profile":"Competency Lead","user_id":64464,"password":"Ypa9os6f","aup_certified":false},
{"first_name":"Hedwig","last_name":"Ferrierio","associate_id":"hferrierio3z","email":"hferrierio3z@tmall.com","role_profile":"Talent Enablement Lead","user_id":121637,"password":"GQXAKjAl9Y","aup_certified":true},
{"first_name":"Abigail","last_name":"Nerney","associate_id":"anerney40","email":"anerney40@biglobe.ne.jp","role_profile":"Associate","user_id":930822,"password":"cVRAirKM","aup_certified":false},
{"first_name":"Kirstyn","last_name":"Matz","associate_id":"kmatz41","email":"kmatz41@adobe.com","role_profile":"Supervisor","user_id":379823,"password":"IVhxIF","aup_certified":true},
{"first_name":"Thomasin","last_name":"Averies","associate_id":"taveries42","email":"taveries42@ycombinator.com","role_profile":"Competency Lead","user_id":140847,"password":"ksERwLth","aup_certified":false},
{"first_name":"Kyla","last_name":"O' Culligan","associate_id":"koculligan43","email":"koculligan43@nba.com","role_profile":"Competency Lead","user_id":442534,"password":"vjiraMS44U","aup_certified":true},
{"first_name":"Regen","last_name":"Carn","associate_id":"rcarn44","email":"rcarn44@prlog.org","role_profile":"Supervisor","user_id":885520,"password":"kVKY8JnA","aup_certified":true},
{"first_name":"Nan","last_name":"Stalman","associate_id":"nstalman45","email":"nstalman45@engadget.com","role_profile":"Talent Enablement Lead","user_id":610378,"password":"2dPYsiDvUD","aup_certified":false},
{"first_name":"Stanislaw","last_name":"Surcombe","associate_id":"ssurcombe46","email":"ssurcombe46@japanpost.jp","role_profile":"Talent Enablement Lead","user_id":368665,"password":"UkH87WD","aup_certified":false},
{"first_name":"Gordan","last_name":"Hodinton","associate_id":"ghodinton47","email":"ghodinton47@eventbrite.com","role_profile":"Associate","user_id":578719,"password":"zxDsuSP1eij","aup_certified":true},
{"first_name":"Maribelle","last_name":"Eixenberger","associate_id":"meixenberger48","email":"meixenberger48@oakley.com","role_profile":"Competency Lead","user_id":842330,"password":"rEnpiqNMNAi","aup_certified":true},
{"first_name":"Rodie","last_name":"Theobald","associate_id":"rtheobald49","email":"rtheobald49@woothemes.com","role_profile":"Talent Enablement Lead","user_id":574930,"password":"1fAwTR9d","aup_certified":true},
{"first_name":"Magnum","last_name":"Thalmann","associate_id":"mthalmann4a","email":"mthalmann4a@blogs.com","role_profile":"Associate","user_id":688696,"password":"edwsDeXXmVq8","aup_certified":false},
{"first_name":"Harlan","last_name":"Bordis","associate_id":"hbordis4b","email":"hbordis4b@narod.ru","role_profile":"Associate","user_id":474195,"password":"qUIlux","aup_certified":true},
{"first_name":"Linnell","last_name":"Calow","associate_id":"lcalow4c","email":"lcalow4c@51.la","role_profile":"Associate","user_id":699010,"password":"6cCtR3","aup_certified":false},
{"first_name":"Stormie","last_name":"Sweetland","associate_id":"ssweetland4d","email":"ssweetland4d@spotify.com","role_profile":"Competency Lead","user_id":367818,"password":"6ozPZHewZ8i8","aup_certified":true},
{"first_name":"Isaac","last_name":"Hastewell","associate_id":"ihastewell4e","email":"ihastewell4e@mac.com","role_profile":"Supervisor","user_id":217946,"password":"jjIPVFk","aup_certified":true},
{"first_name":"Reuben","last_name":"Jaggard","associate_id":"rjaggard4f","email":"rjaggard4f@craigslist.org","role_profile":"Supervisor","user_id":768749,"password":"Zd27lrI","aup_certified":false},
{"first_name":"Meris","last_name":"Patters","associate_id":"mpatters4g","email":"mpatters4g@desdev.cn","role_profile":"Supervisor","user_id":280056,"password":"l4NJsls","aup_certified":true},
{"first_name":"Patsy","last_name":"Jouanny","associate_id":"pjouanny4h","email":"pjouanny4h@nyu.edu","role_profile":"Associate","user_id":508028,"password":"528Jir","aup_certified":false},
{"first_name":"Nana","last_name":"Formoy","associate_id":"nformoy4i","email":"nformoy4i@purevolume.com","role_profile":"Supervisor","user_id":363287,"password":"AzNhe4YpqiP","aup_certified":true},
{"first_name":"Leonard","last_name":"Ossulton","associate_id":"lossulton4j","email":"lossulton4j@php.net","role_profile":"Associate","user_id":426948,"password":"f23guhW4arw4","aup_certified":true},
{"first_name":"Redd","last_name":"Southwick","associate_id":"rsouthwick4k","email":"rsouthwick4k@cdbaby.com","role_profile":"Supervisor","user_id":650029,"password":"CTfasA80","aup_certified":true},
{"first_name":"Tad","last_name":"Mager","associate_id":"tmager4l","email":"tmager4l@networksolutions.com","role_profile":"Competency Lead","user_id":558739,"password":"5NnkhKVqm4","aup_certified":true},
{"first_name":"Farleigh","last_name":"Peyntue","associate_id":"fpeyntue4m","email":"fpeyntue4m@nifty.com","role_profile":"Competency Lead","user_id":346338,"password":"5pP74V","aup_certified":false},
{"first_name":"Sigismund","last_name":"Goodley","associate_id":"sgoodley4n","email":"sgoodley4n@tripod.com","role_profile":"Associate","user_id":881028,"password":"3Z9WmdZgT","aup_certified":true},
{"first_name":"Alvie","last_name":"Alessandrini","associate_id":"aalessandrini4o","email":"aalessandrini4o@mediafire.com","role_profile":"Talent Enablement Lead","user_id":178863,"password":"gXLYDKzIs","aup_certified":false},
{"first_name":"Teodoor","last_name":"Constantine","associate_id":"tconstantine4p","email":"tconstantine4p@webeden.co.uk","role_profile":"Competency Lead","user_id":376537,"password":"soakBnZ","aup_certified":true},
{"first_name":"Leisha","last_name":"Esmonde","associate_id":"lesmonde4q","email":"lesmonde4q@amazonaws.com","role_profile":"Associate","user_id":510734,"password":"CWl9HE","aup_certified":true},
{"first_name":"Gregoor","last_name":"Buyers","associate_id":"gbuyers4r","email":"gbuyers4r@addtoany.com","role_profile":"Talent Enablement Lead","user_id":167051,"password":"1i38VSgr","aup_certified":false},
{"first_name":"Ulrich","last_name":"Glossop","associate_id":"uglossop4s","email":"uglossop4s@blogs.com","role_profile":"Supervisor","user_id":861035,"password":"smNu82j","aup_certified":false},
{"first_name":"Web","last_name":"Buxy","associate_id":"wbuxy4t","email":"wbuxy4t@usda.gov","role_profile":"Competency Lead","user_id":127741,"password":"nUnWWDa","aup_certified":false},
{"first_name":"Wanids","last_name":"Backsal","associate_id":"wbacksal4u","email":"wbacksal4u@apple.com","role_profile":"Associate","user_id":890611,"password":"Ezxn80kq8ZW","aup_certified":true},
{"first_name":"Vinny","last_name":"Keetley","associate_id":"vkeetley4v","email":"vkeetley4v@list-manage.com","role_profile":"Talent Enablement Lead","user_id":142575,"password":"GPQCJE4UHqd","aup_certified":true},
{"first_name":"Tommie","last_name":"Shurrocks","associate_id":"tshurrocks4w","email":"tshurrocks4w@blogtalkradio.com","role_profile":"Competency Lead","user_id":733599,"password":"nLo4g4uzZmq","aup_certified":true},
{"first_name":"Lynne","last_name":"Stentiford","associate_id":"lstentiford4x","email":"lstentiford4x@addtoany.com","role_profile":"Supervisor","user_id":816094,"password":"3I8QXiTL","aup_certified":false},
{"first_name":"Marylee","last_name":"Shulem","associate_id":"mshulem4y","email":"mshulem4y@salon.com","role_profile":"Talent Enablement Lead","user_id":445772,"password":"mrdLvclrBZZ","aup_certified":false},
{"first_name":"Giacopo","last_name":"Yakunkin","associate_id":"gyakunkin4z","email":"gyakunkin4z@icq.com","role_profile":"Associate","user_id":846369,"password":"8SxRbo7oK7","aup_certified":true},
{"first_name":"Putnam","last_name":"Swede","associate_id":"pswede50","email":"pswede50@tamu.edu","role_profile":"Talent Enablement Lead","user_id":950195,"password":"1D8f644","aup_certified":false},
{"first_name":"Ronnica","last_name":"Blodgett","associate_id":"rblodgett51","email":"rblodgett51@hhs.gov","role_profile":"Supervisor","user_id":31291,"password":"MLP7u6Q","aup_certified":true},
{"first_name":"Francisco","last_name":"Wych","associate_id":"fwych52","email":"fwych52@bbc.co.uk","role_profile":"Talent Enablement Lead","user_id":759435,"password":"9gdyR8K","aup_certified":true},
{"first_name":"Charmine","last_name":"Thon","associate_id":"cthon53","email":"cthon53@springer.com","role_profile":"Supervisor","user_id":682825,"password":"n7aXartwX","aup_certified":false},
{"first_name":"Amelina","last_name":"Jovey","associate_id":"ajovey54","email":"ajovey54@blogs.com","role_profile":"Associate","user_id":53744,"password":"pCWiXZcAj","aup_certified":true},
{"first_name":"Remus","last_name":"Konig","associate_id":"rkonig55","email":"rkonig55@chronoengine.com","role_profile":"Associate","user_id":397005,"password":"rOkU0M","aup_certified":false},
{"first_name":"Thomasin","last_name":"Coffey","associate_id":"tcoffey56","email":"tcoffey56@jimdo.com","role_profile":"Competency Lead","user_id":814001,"password":"gHUlB6","aup_certified":true},
{"first_name":"Livia","last_name":"Shernock","associate_id":"lshernock57","email":"lshernock57@mozilla.org","role_profile":"Competency Lead","user_id":457794,"password":"yWmZ5Khd","aup_certified":true},
{"first_name":"Jocelyn","last_name":"Simonin","associate_id":"jsimonin58","email":"jsimonin58@hud.gov","role_profile":"Talent Enablement Lead","user_id":412844,"password":"bAjyEr","aup_certified":false},
{"first_name":"Gwenette","last_name":"Hubner","associate_id":"ghubner59","email":"ghubner59@deliciousdays.com","role_profile":"Supervisor","user_id":848408,"password":"BFiSmZdo8Zq","aup_certified":false},
{"first_name":"Alexine","last_name":"Magnar","associate_id":"amagnar5a","email":"amagnar5a@seesaa.net","role_profile":"Competency Lead","user_id":764420,"password":"QRrDnyIewi","aup_certified":false},
{"first_name":"Mariel","last_name":"Dredge","associate_id":"mdredge5b","email":"mdredge5b@earthlink.net","role_profile":"Talent Enablement Lead","user_id":786959,"password":"Sr7ddHM0Fn","aup_certified":false},
{"first_name":"Odilia","last_name":"Haygreen","associate_id":"ohaygreen5c","email":"ohaygreen5c@nbcnews.com","role_profile":"Associate","user_id":406053,"password":"JXCCFSWb5F","aup_certified":false},
{"first_name":"Melodie","last_name":"Birmingham","associate_id":"mbirmingham5d","email":"mbirmingham5d@aboutads.info","role_profile":"Competency Lead","user_id":46689,"password":"dVVXPEG3h","aup_certified":false},
{"first_name":"Marian","last_name":"Marrison","associate_id":"mmarrison5e","email":"mmarrison5e@hhs.gov","role_profile":"Associate","user_id":140332,"password":"UFmUls","aup_certified":false},
{"first_name":"Ignazio","last_name":"Crafts","associate_id":"icrafts5f","email":"icrafts5f@squidoo.com","role_profile":"Associate","user_id":171085,"password":"CrCvkL","aup_certified":false},
{"first_name":"Dominik","last_name":"Olensby","associate_id":"dolensby5g","email":"dolensby5g@census.gov","role_profile":"Talent Enablement Lead","user_id":449706,"password":"13fVo7vL","aup_certified":false},
{"first_name":"Lenci","last_name":"Wink","associate_id":"lwink5h","email":"lwink5h@berkeley.edu","role_profile":"Associate","user_id":476464,"password":"tQQafpXU","aup_certified":true},
{"first_name":"Kissiah","last_name":"Crake","associate_id":"kcrake5i","email":"kcrake5i@sourceforge.net","role_profile":"Associate","user_id":793124,"password":"2w3JMhHU","aup_certified":true},
{"first_name":"Willey","last_name":"Ruffli","associate_id":"wruffli5j","email":"wruffli5j@princeton.edu","role_profile":"Competency Lead","user_id":475012,"password":"5oFyoM3","aup_certified":true}]